stopments/__init__.py
stopments/__version__.py
stopments/elements.py
stopments/embed/__init__.py
stopments/py.typed
stopments/scalar.py
stopments/static/favicon.ico
stopments/static/scalar-api-reference.js
stopments/static/styles.min.css
stopments/static/web-components.min.js
stopments-25.10.1.dist-info/WHEEL
stopments-25.10.1.dist-info/METADATA
stopments-25.10.1.dist-info/RECORD
