Metadata-Version: 2.3
Name: stopments
Version: 25.10.1
Summary: Stoplight elements html
Keywords: stoplight,elements,openapi,swagger
Author: Dowon
Author-email: Dowon <ks2515@naver.com>
License: BSD-2-Clause
Classifier: Framework :: FastAPI
Classifier: Programming Language :: Python :: 3
Classifier: Topic :: Documentation
Requires-Python: >=3.9
Project-URL: Repository, https://github.com/Bing-su/stopments
